libpyinfinite/__init__.py
libpyinfinite/module/__init__.py
libpyinfinite/module/module.py
libpyinfinite/module/moduleBlockHeader.py
libpyinfinite/module/moduleFile.py
libpyinfinite/module/moduleHeader.py
libpyinfinite/module/moduleLoader.py
libpyinfinite/module/oodle/oodleDecompressor.py
libpyinfinite/reader/__init__.py
libpyinfinite/reader/common.py
libpyinfinite/tag/__init__.py
libpyinfinite/tag/tag.py
libpyinfinite/tag/tagDataBlock.py
libpyinfinite/tag/tagDataReference.py
libpyinfinite/tag/tagDependency.py
libpyinfinite/tag/tagHeader.py
libpyinfinite/tag/tagReference.py
libpyinfinite/tag/tagStruct.py
libpyinfinite/tag/tagTypes.py
libpyinfinite/tag/definitions/__init__.py
libpyinfinite/tag/definitions/cmsw.py
libpyinfinite/tag/definitions/mat.py
libpyinfinite/tag/definitions/rucs.py
libpyinfinite/tag/definitions/rucy.py
libpyinfinite/tag/structs/__init__.py
libpyinfinite/tag/structs/anyTag.py
libpyinfinite/tag/structs/infiniteStructs.py
libpyinfinite/tag/zonesets/__init__.py
libpyinfinite/tag/zonesets/zonesetHeader.py
libpyinfinite/tag/zonesets/zonesetInstance.py
libpyinfinite/tag/zonesets/zonesetInstanceHeader.py
libpyinfinite/tag/zonesets/zonesetTag.py
libpyinfinite-0.0.5.dist-info/METADATA
libpyinfinite-0.0.5.dist-info/WHEEL
libpyinfinite-0.0.5.dist-info/licenses/LICENSE
libpyinfinite-0.0.5.dist-info/RECORD
