Metadata-Version: 2.3
Name: libpyinfinite
Version: 0.0.5
Summary: Python library for parsing binary files from Halo Infinite.
Project-URL: Repository, https://github.com/Surasia/libpyinfinite
Project-URL: Issues, https://github.com/Surasia/libpyinfinite/issues
Project-URL: Changelog, https://github.com/Surasia/libpyinfinite/blob/main/CHANGELOG.md
Author: Surasia
License:                     GNU GENERAL PUBLIC LICENSE
License-File: LICENSE
Keywords: Halo,Halo Infinite,Module,Tags
Classifier: Development Status :: 3 - Alpha
Classifier: Intended Audience :: Developers
Classifier: License :: OSI Approved :: GNU General Public License v3 (GPLv3)
Classifier: Operating System :: Microsoft :: Windows
Classifier: Programming Language :: Python :: 3.11
Classifier: Programming Language :: Python :: 3.12
Classifier: Typing :: Typed
Requires-Python: >=3.11.0
